MANIFEST.in
README.rst
resources.py
setup.py
tox.ini
python_resources.egg-info/PKG-INFO
python_resources.egg-info/SOURCES.txt
python_resources.egg-info/dependency_links.txt
python_resources.egg-info/top_level.txt