Metadata-Version: 1.0
Name: python-resources
Version: 0.2
Summary:  A fixture lifecycle management library for your tests
Home-page: https://github.com/doist/resources
Author: Roman Imankulov
Author-email: roman.imankulov@gmail.com
License: BSD
Platform: UNKNOWN
Classifier: Development Status :: 4 - Beta
Classifier: Intended Audience :: Developers
Classifier: License :: OSI Approved :: BSD License
Classifier: Programming Language :: Python
Classifier: Programming Language :: Python :: 2.6
Classifier: Programming Language :: Python :: 2.7
Classifier: Programming Language :: Python :: 3.3
Classifier: Topic :: Software Development :: Testing
